{
  "item.b:amethyst_netherite_sword": "紫水玉玄鈺劍",
  "item.b:amethyst_netherite_shovel": "紫水玉玄鈺鍁",
  "item.b:amethyst_netherite_pickaxe": "紫水玉玄鈺鎬",
  "item.b:amethyst_netherite_axe": "紫水玉玄鈺斧",
  "item.b:amethyst_netherite_hoe": "紫水玉玄鈺鋤",
  "item.b:amethyst_netherite_helmet": "紫水玉玄鈺胄",
  "item.b:amethyst_netherite_chestplate": "紫水玉玄鈺鎧",
  "item.b:amethyst_netherite_leggings": "紫水玉玄鈺護腿",
  "item.b:amethyst_netherite_boots": "紫水玉玄鈺靴",
  "item.b:copper_netherite_sword": "銅玄鈺劍",
  "item.b:copper_netherite_shovel": "銅玄鈺鍁",
  "item.b:copper_netherite_pickaxe": "銅玄鈺鎬",
  "item.b:copper_netherite_axe": "銅玄鈺斧",
  "item.b:copper_netherite_hoe": "銅玄鈺鋤",
  "item.b:copper_netherite_helmet": "銅玄鈺胄",
  "item.b:copper_netherite_chestplate": "銅玄鈺鎧",
  "item.b:copper_netherite_leggings": "銅玄鈺護腿",
  "item.b:copper_netherite_boots": "銅玄鈺靴",
  "item.b:golden_netherite_sword": "金玄鈺劍",
  "item.b:golden_netherite_shovel": "金玄鈺鍁",
  "item.b:golden_netherite_pickaxe": "金玄鈺鎬",
  "item.b:golden_netherite_axe": "金玄鈺斧",
  "item.b:golden_netherite_hoe": "金玄鈺鋤",
  "item.b:golden_netherite_helmet": "金玄鈺胄",
  "item.b:golden_netherite_chestplate": "金玄鈺鎧",
  "item.b:golden_netherite_leggings": "金玄鈺護腿",
  "item.b:golden_netherite_boots": "金玄鈺靴",
  "item.b:emerald_netherite_sword": "祖母綠玄鈺劍",
  "item.b:emerald_netherite_shovel": "祖母綠玄鈺鍁",
  "item.b:emerald_netherite_pickaxe": "祖母綠玄鈺鎬",
  "item.b:emerald_netherite_axe": "祖母綠玄鈺斧",
  "item.b:emerald_netherite_hoe": "祖母綠玄鈺鋤",
  "item.b:emerald_netherite_helmet": "祖母綠玄鈺胄",
  "item.b:emerald_netherite_chestplate": "祖母綠玄鈺鎧",
  "item.b:emerald_netherite_leggings": "祖母綠玄鈺護腿",
  "item.b:emerald_netherite_boots": "祖母綠玄鈺靴",
  "item.b:iron_netherite_sword": "鐵玄鈺劍",
  "item.b:iron_netherite_shovel": "鐵玄鈺鍁"
}